{
  "offerDate": "",
  "buyerName": "",
  "buyer2Name": "",
  "sellerName": "",
  "seller2Name": "",
  "addressLine1": "",
  "unitNumber": "",
  "city": "",
  "zipCode": "",
  "taxMapId": "",
  "section": "",
  "subdivision_or_condominium": "",
  "parking_spaces": "",
  "county": "",
  "deedBook": "",
  "page_folio": "",
  "sales_price": "",
  "sellerSubsidyAmount": "",
  "brokerCompPayment": "",
  "listingBrokerage": "",
  "buyersBrokerage": "",
  "ratificationDate": "",
  "appraisalContingency": "",
  "willProvideAppraisalAccess": "",
  "primaryResidence": "",
  "noteAmount": "",
  "emdAmount": "",
  "checkOrWired": "",
  "notePayableDate": "",
  "depositDeliveredTo": "",
  "otherEMDRecipient": "",
  "settlementDate": "",
  "settlementAgent": "",
  "resalePkgToSeller": "",
  "resalePkgToSellerText": "",
  "generalDeliveryToSeller": "",
  "generalDeliveryToBuyer": "",
  "hoa": "",
  "condo": "",
  "daysResaleDiscCancelBeforeRatification": "",
  "daysResaleDiscCancelAfterRatification": "",
  "resalePkgToBuyerElectronic": "",
  "resalePkgToBuyerHardCopy": "",
  "sellerDeliverPropertyDebris": "",
  "otherDateSellerDeliverPropertyDebris": "",
  "inspectionContingency": "",
  "sellerProvidesPropertyAccessBeginDate": "",
  "sellerProvidesPropertyAccessEndDate": "",
  "waterSupply": "",
  "hotWater": "",
  "hotWaterOther": "",
  "airConditioning": "",
  "heating": "",
  "sewage": "",
  "appliancesAndPropertyConveyed": "",
  "alarmSystemQuantity": "",
  "builtInMicrowaveQuantity": "",
  "celingFanQuantity": "",
  "centralVacuumQuantity": "",
  "clothesDryerQuantity": "",
  "clothesWasherQuantity": "",
  "cooktopQuantity": "",
  "dishwasherQuantity": "",
  "disposerQuantity": "",
  "electronicAirFilterQuantity": "",
  "fireplaceScreenDoorQuantity": "",
  "freezerQuantity": "",
  "furnaceHumidifierQuantity": "",
  "garageOpenerQuantity": "",
  "garageOpenerRemoteQuantity": "",
  "gasLogQuantity": "",
  "hotTubEquipmentOrCoverQuantity": "",
  "intercomQuantity": "",
  "playgroundEquipmentQuantity": "",
  "poolEquipmentOrCoverQuantity": "",
  "refrigeratorQuantity": "",
  "iceMakerQuantity": "",
  "satelliteDishQuantity": "",
  "storageShedQuantity": "",
  "stoveOrRangeQuantity": "",
  "wallOvenQuantity": "",
  "waterTreatmentSystemQuantity": "",
  "windowACUnitQuantity": "",
  "windowFanQuantity": "",
  "windowTreatmentQuantity": "",
  "woodStoveQuantity": "",
  "otherAirConditioningType": "",
  "otherHeatingType": "",
  "numberBedroomsWithSeptic": "",
  "numberOfACZones": "",
  "numberOfHeatingZones": "",
  "numberOfBedroomsWithAltSeptic": "",
  "otherConveyances": "",
  "itemsThatDontConvey": "",
  "fuelTanks": "",
  "fuelTanksLeasedQuantity": "",
  "fuelTanksOwnedQuantity": "",
  "leasedItems": "",
  "yearBuiltForLead1978": "",
  "leadBasedInspection": "",
  "termiteInspection": "",
  "homeWarranty": "",
  "homeWarrantySelectedBy": "",
  "homeWarrantyPaidBy": "",
  "maxCostOfWarranty": "",
  "warrantyProvider": "",
  "buyerOrSellerRealEstateLicenseActive": "",
  "buyerOrSellerNamesIfLicensedRealtors": "",
  "buyerOrSellerLicensedInState": "",
  "transactionPartiesAreRelated": "",
  "buyerOrSellerLicensedOtherStateName": "",
  "additionalForms": "",
  "otherForm": "",
  "listingOfficeName": "",
  "buyerBrokerageAddress": "",
  "listingBrokerageAddress": "",
  "listingOffice_phone": "",
  "listingBrokerMLSBrokerCode": "",
  "listingVAFirmLicenseNo": "",
  "listingAgentName": "",
  "listingAgentEmail": "",
  "listingAgentPhone": "",
  "listingAgentMLSID": "",
  "listingAgentLicenseNo": "",
  "listingAgentTeamName": "",
  "listingAgentTeamBusinessLicenseNo": "",
  "buyerBrokeragePhone": "",
  "buyerBrokerMLSBrokerCode": "",
  "buyerVAFirmLicenseNo": "",
  "buyerAgentName": "",
  "buyerAgentEmail": "",
  "buyerAgentPhone": "",
  "buyerAgentMLSID": "",
  "buyerAgentLicenseNo": "",
  "buyerAgentTeamName": "",
  "buyerAgentTeamBusinessLicenseNo": "",
  "legalDescriptionLot": "",
  "downPaymentAmount": "",
  "financingAmount": "",
  "secondTrustAmount": "",
  "sellerHeldTrust": "",
  "totalFinancing": "",
  "downPaymentPercent": "",
  "financingPercent": "",
  "secondTrustPercent": "",
  "sellerHeldTrustPercent": "",
  "totalFinancingPercent": "",
  "sellerSubsidyToBuyerPercent": "",
  "brokerCompPaymentPercent": "",
  "financingType": "",
  "otherFinancingType": "",
  "financingContingency": "",
  "buyerDeliveredToEscrowAgent": "",
  "noOfDaysInDepositDelivery": "",
  "sellerProvidesPropertyAccess": "",
  "seller1Signature": "",
  "buyer1Signature": "",
  "seller2Signature": "",
  "buyer2Signature": "",
  "seller1Date": "",
  "buyer1Date": "",
  "buyer2Date": "",
  "seller2Date": ""
}


